deeplearningtools/__init__.py
deeplearningtools/framework.py
deeplearningtools-0.1.1.dist-info/METADATA
deeplearningtools-0.1.1.dist-info/WHEEL
deeplearningtools-0.1.1.dist-info/RECORD
